passfd.so
passfd-1.0.2.dist-info/LICENSE.txt
passfd-1.0.2.dist-info/METADATA
passfd-1.0.2.dist-info/WHEEL
passfd-1.0.2.dist-info/top_level.txt
passfd-1.0.2.dist-info/RECORD
